{
  "baseCurrency": "INR",
  "lastUpdated": "2024-08-19T12:16:53.643Z",
  "date": "2024-08-19",
  "rates": [
    {
      "currency": "USD",
      "value": 83.89
    },
    {
      "currency": "EUR",
      "value": 92.62
    },
    {
      "currency": "GBP",
      "value": 108.65
    },
    {
      "currency": "JPY",
      "value": 0.57
    },
    {
      "currency": "AUD",
      "value": 56.18
    },
    {
      "currency": "CAD",
      "value": 61.34
    },
    {
      "currency": "CHF",
      "value": 96.97
    },
    {
      "currency": "SEK",
      "value": 8.06
    },
    {
      "currency": "NZD",
      "value": 50.97
    },
    {
      "currency": "MXN",
      "value": 4.49
    },
    {
      "currency": "SGD",
      "value": 64.03
    },
    {
      "currency": "HKD",
      "value": 10.76
    },
    {
      "currency": "NOK",
      "value": 7.89
    },
    {
      "currency": "KRW",
      "value": 0.06
    },
    {
      "currency": "TRY",
      "value": 2.49
    },
    {
      "currency": "RUB",
      "value": 0.93
    }
  ]
}