{
  "baseCurrency": "INR",
  "lastUpdated": "2024-09-11T12:17:04.850Z",
  "date": "2024-09-11",
  "rates": [
    {
      "currency": "USD",
      "value": 84
    },
    {
      "currency": "EUR",
      "value": 92.75
    },
    {
      "currency": "GBP",
      "value": 109.91
    },
    {
      "currency": "JPY",
      "value": 0.59
    },
    {
      "currency": "AUD",
      "value": 56.01
    },
    {
      "currency": "CAD",
      "value": 61.85
    },
    {
      "currency": "CHF",
      "value": 99.12
    },
    {
      "currency": "CNY",
      "value": 11.81
    },
    {
      "currency": "SEK",
      "value": 8.11
    },
    {
      "currency": "NZD",
      "value": 51.63
    },
    {
      "currency": "MXN",
      "value": 4.22
    },
    {
      "currency": "SGD",
      "value": 64.48
    },
    {
      "currency": "HKD",
      "value": 10.77
    },
    {
      "currency": "NOK",
      "value": 7.77
    },
    {
      "currency": "KRW",
      "value": 0.06
    },
    {
      "currency": "TRY",
      "value": 2.47
    },
    {
      "currency": "RUB",
      "value": 0.92
    }
  ]
}